kizhiview/__init__.py
kizhiview/problems/__init__.py
kizhiview/problems/palindrome.py
kizhiview-0.1.2.dist-info/METADATA
kizhiview-0.1.2.dist-info/WHEEL
kizhiview-0.1.2.dist-info/top_level.txt
kizhiview-0.1.2.dist-info/RECORD
